isover10/__init__.py
isover10/isoverlap.py
isover10/isoverlapV2.py
isover10-0.1.5.dist-info/LICENSE.txt
isover10-0.1.5.dist-info/METADATA
isover10-0.1.5.dist-info/WHEEL
isover10-0.1.5.dist-info/top_level.txt
isover10-0.1.5.dist-info/RECORD
