Metadata-Version: 2.1
Name: isover10
Version: 0.1.5
Summary: Check whether two lines A (x1,x2) and B (x3,x4) on the x-axis whether they overlap or not
Home-page: https://github.com/miguelluiz/overlap
Author: Miguel Almeida
Author-email: mplabdev@gmail.com
License: MIT
Download-URL: https://github.com/miguelluiz/overlap/archive/v_01.tar.gz
Keywords: Overlap,A over B
Platform: UNKNOWN
Classifier: Development Status :: 3 - Alpha
Classifier: Intended Audience :: Developers
Classifier: Topic :: Software Development :: Build Tools
Classifier: Topic :: Software Development :: Internationalization
Classifier: Operating System :: OS Independent
Classifier: License :: OSI Approved :: MIT License
Classifier: Programming Language :: Python :: 3
Classifier: Programming Language :: Python :: 3.4
Classifier: Programming Language :: Python :: 3.5
Classifier: Programming Language :: Python :: 3.6
Classifier: Programming Language :: Python :: 3.7
